tests/__init__.py
tests/test_index.py
tests/test_relevance.py
tests/test_retrieval.py
wiki_passage_retriever/__init__.py
wiki_passage_retriever/dpr_tokenizer.py
wiki_passage_retriever/index.py
wiki_passage_retriever/retrieve.py
wiki_passage_retriever/utils.py
wiki_passage_retriever/_cli/__init__.py
wiki_passage_retriever/_cli/index.py
wiki_passage_retriever/_cli/indexed_retrieve.py
wiki_passage_retriever/_cli/retrieve.py
wiki_passage_retriever-0.1.4.dist-info/LICENSE
wiki_passage_retriever-0.1.4.dist-info/METADATA
wiki_passage_retriever-0.1.4.dist-info/WHEEL
wiki_passage_retriever-0.1.4.dist-info/entry_points.txt
wiki_passage_retriever-0.1.4.dist-info/top_level.txt
wiki_passage_retriever-0.1.4.dist-info/RECORD
